sc3vn/__init__.py
sc3vn/functions.py
sc3vn-0.1.0.dist-info/METADATA
sc3vn-0.1.0.dist-info/WHEEL
sc3vn-0.1.0.dist-info/licenses/LICENSE.txt
sc3vn-0.1.0.dist-info/RECORD
